tdi_rust_python_tools-0.9.3.dist-info/METADATA
tdi_rust_python_tools-0.9.3.dist-info/WHEEL
tdi_rust_python_tools/__init__.py
tdi_rust_python_tools/__init__.pyi
tdi_rust_python_tools/py.typed
tdi_rust_python_tools/tdi_rust_python_tools.cpython-313-i386-linux-gnu.so
tdi_rust_python_tools-0.9.3.dist-info/RECORD
