Metadata-Version: 2.4
Name: tdi_rust_python_tools
Version: 0.9.3
Classifier: Programming Language :: Rust
Classifier: Programming Language :: Python :: Implementation :: CPython
Classifier: Programming Language :: Python :: Implementation :: PyPy
Summary: Rust-based Python tools for faster processing of data.
Requires-Python: >=3.13
